PyThreadKiller/__init__.py
PyThreadKiller/main.py
pythreadkiller-3.0.8.dist-info/LICENSE
pythreadkiller-3.0.8.dist-info/METADATA
pythreadkiller-3.0.8.dist-info/WHEEL
pythreadkiller-3.0.8.dist-info/top_level.txt
pythreadkiller-3.0.8.dist-info/RECORD
