Metadata-Version: 2.1
Name: pythreadkiller
Version: 3.0.8
Summary: A utility to manage and kill threads in Python applications
Home-page: https://github.com/kumarmuthu/PyThreadKiller
Author: Muthukumar Subramanian
Author-email: kumarmuthuece5@gmail.com
Project-URL: Homepage, https://github.com/kumarmuthu/PyThreadKiller
Project-URL: Source, https://github.com/kumarmuthu/PyThreadKiller
Project-URL: Tracker, https://github.com/kumarmuthu/PyThreadKiller/issues
Classifier: Development Status :: 3 - Alpha
Classifier: Intended Audience :: Developers
Classifier: License :: OSI Approved :: MIT License
Classifier: Programming Language :: Python :: 3
Classifier: Programming Language :: Python :: 3.8
Classifier: Programming Language :: Python :: 3.9
Classifier: Programming Language :: Python :: 3.10
Classifier: Programming Language :: Python :: 3.11
Classifier: Programming Language :: Python :: 3.12
Requires-Python: >=3.8
License-File: LICENSE
